mapchartpy/__init__.py
mapchartpy/save.py
mapchartpy/savefile.py
mapchartpy-0.0.3.dist-info/METADATA
mapchartpy-0.0.3.dist-info/WHEEL
mapchartpy-0.0.3.dist-info/licenses/LICENSE
mapchartpy-0.0.3.dist-info/RECORD
