Metadata-Version: 2.4
Name: mapchartpy
Version: 0.0.3
Summary: Some utilities for modifying or creating save files from mapchart.net
Project-URL: Homepage, https://github.com/ctih1/mapchart-py
Project-URL: Issues, https://github.com/ctih1/mapchart-py/issues
Author-email: ctih1 <onni09nevala@gmail.com>
License-Expression: MIT
License-File: LICENSE
Classifier: Operating System :: OS Independent
Classifier: Programming Language :: Python :: 3
Requires-Python: >=3.9
